<?xml version="1.0" encoding="utf-8"?>
<LanguageData>

  <AEXP_TailedBiped.label>хвостатое двуногое</AEXP_TailedBiped.label>
  <AEXP_TailedBiped.corePart.parts.4>левое лёгкое</AEXP_TailedBiped.corePart.parts.4>
  <AEXP_TailedBiped.corePart.parts.5>правое лёгкое</AEXP_TailedBiped.corePart.parts.5>
  <AEXP_TailedBiped.corePart.parts.6>левая почка</AEXP_TailedBiped.corePart.parts.6>
  <AEXP_TailedBiped.corePart.parts.7>правая почка</AEXP_TailedBiped.corePart.parts.7>
  <AEXP_TailedBiped.corePart.parts.Neck.parts.0.parts.1>левый глаз</AEXP_TailedBiped.corePart.parts.Neck.parts.0.parts.1>
  <AEXP_TailedBiped.corePart.parts.Neck.parts.0.parts.2>правый глаз</AEXP_TailedBiped.corePart.parts.Neck.parts.0.parts.2>
  <AEXP_TailedBiped.corePart.parts.Neck.parts.0.parts.3>левое ухо</AEXP_TailedBiped.corePart.parts.Neck.parts.0.parts.3>
  <AEXP_TailedBiped.corePart.parts.Neck.parts.0.parts.4>правое ухо</AEXP_TailedBiped.corePart.parts.Neck.parts.0.parts.4>
  <AEXP_TailedBiped.corePart.parts.8>левая рука</AEXP_TailedBiped.corePart.parts.8>
  <AEXP_TailedBiped.corePart.parts.9>правая рука</AEXP_TailedBiped.corePart.parts.9>
  <AEXP_TailedBiped.corePart.parts.10>левая нога</AEXP_TailedBiped.corePart.parts.10>
  <AEXP_TailedBiped.corePart.parts.11>правая нога</AEXP_TailedBiped.corePart.parts.11>

</LanguageData>