<?xml version="1.0" encoding="utf-8"?>
<LanguageData>
  <!-- EN: Switch to Full Dialog -->
  <VUIE.FloatMenus.SwitchToFull>Раскрыть диалог</VUIE.FloatMenus.SwitchToFull>
  <!-- EN: Page {0} of {1} -->
  <VUIE.PageOf>Страница {0} из {1}</VUIE.PageOf>
  <!-- EN: Feeling depressed -->
  <VUIE.Moods.Extreme>В депрессии</VUIE.Moods.Extreme>
  <!-- EN: Feeling unhappy -->
  <VUIE.Moods.Major>Несчастны</VUIE.Moods.Major>
  <!-- EN: Feeling stressed -->
  <VUIE.Moods.Minor>В стрессе</VUIE.Moods.Minor>
  <!-- EN: Feeling happy -->
  <VUIE.Moods.VeryHigh>Счастливы</VUIE.Moods.VeryHigh>
  <!-- EN: Feeling content -->
  <VUIE.Moods.High>Удовлетворены</VUIE.Moods.High>
  <!-- EN: Feeling indifferent -->
  <VUIE.Moods.Neutral>Безразличны</VUIE.Moods.Neutral>
  <!-- EN: Vanilla UI Expanded -->
  <VUIE>Vanilla UI Expanded</VUIE>
  <!-- EN: {0}h {1}/{2}/{3} -->
  <VUIE.DateTiny>{0}ч. {1}/{2}/{3}</VUIE.DateTiny>
  <!-- EN: Minimize -->
  <VUIE.Minimize>Уменьшить</VUIE.Minimize>
  <!-- EN: Maximize -->
  <VUIE.Maximizie>Увеличить</VUIE.Maximizie>
  <!-- EN: Add to Favorites -->
  <VUIE.Favorite>Добавить в избранное</VUIE.Favorite>
  <!-- EN: Remove from Favorites -->
  <VUIE.UnFavorite>Удалить из избранного</VUIE.UnFavorite>
  <!-- EN: Search: -->
  <VUIE.Search>Поиск:</VUIE.Search>
  <!-- EN: Restoring architect preset -->
  <VUIE.Architect.RestoringSettings>Восстановить настройки «проектов»</VUIE.Architect.RestoringSettings>
</LanguageData>