<?xml version="1.0" encoding="utf-8"?>
<LanguageData>
  <!-- EN: light plate helmet -->
  <VFEM_Apparel_PlateHelmetLight.label>лёгкий пластинчатый шлем</VFEM_Apparel_PlateHelmetLight.label>
  <!-- EN: A lightweight medieval helmet that provides moderate protection against sharp attacks. Not effective against blunt weapons. Slighty restricts the wearer's field of vision. -->
  <VFEM_Apparel_PlateHelmetLight.description>Лёгкий средневековый шлем, дающий умеренную защиту от проникающих ранений. Неэффективен против дробящих ударов. Слегка ограничивает обзор.</VFEM_Apparel_PlateHelmetLight.description>

  <!-- EN: heavy plate helmet -->
  <VFEM_Apparel_PlateHelmetHeavy.label>тяжёлый пластинчатый шлем</VFEM_Apparel_PlateHelmetHeavy.label>
  <!-- EN: A bulky medieval helmet that provides full-head coverage. Offers a considerable amount of protection but restricts the wearer's field of vision. -->
  <VFEM_Apparel_PlateHelmetHeavy.description>Громоздкий средневековый шлем, полностью закрывающий голову. Обеспечивает значительную защиту, но ограничивает обзор.</VFEM_Apparel_PlateHelmetHeavy.description>

  <!-- EN: jester hat -->
  <VFEM_Apparel_JesterHat.label>шутовской колпак</VFEM_Apparel_JesterHat.label>
  <!-- EN: A hat worthy of a jester. Each half is different from the other one in color. -->
  <VFEM_Apparel_JesterHat.description>Шляпа, достойная шута. Сшита из ткани разных цветов.</VFEM_Apparel_JesterHat.description>

  <!-- EN: dame hat -->
  <VFEM_Apparel_DameHat.label>дамская шляпа</VFEM_Apparel_DameHat.label>
  <!-- EN: A beautiful long cone hat for a dame. -->
  <VFEM_Apparel_DameHat.description>Красивый конусообразный головной убор для настоящих дам.</VFEM_Apparel_DameHat.description>

  <!-- EN: king's crown -->
  <VFEM_Apparel_KingsCrown.label>корона</VFEM_Apparel_KingsCrown.label>
  <!-- EN: A beautiful metal crown. The wearer becomes very influential, but at the same time they will refuse to do any work. -->
  <VFEM_Apparel_KingsCrown.description>Красивая металлическая корона. Владелец становится очень влиятельным, но в то же время отказывается выполнять любую работу.</VFEM_Apparel_KingsCrown.description>

  <!-- EN: plague mask -->
  <VFEM_Apparel_PlagueMask.label>маска чумного доктора</VFEM_Apparel_PlagueMask.label>
  <!-- EN: A mask with a long ‘beak’ filled with herbal medicine that keeps infected pawns at a distance. -->
  <VFEM_Apparel_PlagueMask.description>Маска с «птичьим клювом», наполненным лекарственными травами, для защиты от чёрной чумы или для предотвращения её распространения, если носящий маску уже заражён.</VFEM_Apparel_PlagueMask.description>
</LanguageData>