<?xml version="1.0" encoding="utf-8"?>
<LanguageData>

  <!-- EN: moa egg (fert.) -->
  <AEXP_EggMoaFertilized.label>яйцо моа (опл.)</AEXP_EggMoaFertilized.label>
  <!-- EN: A fertilized moa egg. If all goes well, it should hatch into a baby moa. It can be eaten raw, but it's much better cooked. -->
  <AEXP_EggMoaFertilized.description>Оплодотворённое яйцо моа. Если всё пойдёт хорошо, в скором времени из него вылупится птенец моа. Может быть съедено сырым, но приготовленное оно гораздо вкуснее.</AEXP_EggMoaFertilized.description>
  <!-- EN: moa egg (unfert.) -->
  <AEXP_EggMoaUnfertilized.label>яйцо моа (неопл.)</AEXP_EggMoaUnfertilized.label>
  <!-- EN: An unfertilized moa egg. It can be eaten raw, but it's much better cooked. -->
  <AEXP_EggMoaUnfertilized.description>Неоплодотворённое яйцо моа. Может быть съедено сырым, но приготовленное оно гораздо вкуснее.</AEXP_EggMoaUnfertilized.description>


  <!-- EN: rockhopper penguin egg (fert.) -->
  <AEXP_EggRockhopperPenguinFertilized.label>яйцо хохлатого пингвина (опл.)</AEXP_EggRockhopperPenguinFertilized.label>
  <!-- EN: A fertilized rockhopper penguin egg. If all goes well, it should hatch into a baby rockhopper penguin. It can be eaten raw, but it's much better cooked. -->
  <AEXP_EggRockhopperPenguinFertilized.description>Оплодотворённое яйцо хохлатого пингвина. Если всё пойдёт хорошо, в скором времени из него вылупится детёныш хохлатого пингвина. Может быть съедено сырым, но приготовленное оно гораздо вкуснее.</AEXP_EggRockhopperPenguinFertilized.description>
  <!-- EN: rockhopper penguin egg (unfert.) -->
  <AEXP_EggRockhopperPenguinUnfertilized.label>rockhopper penguin egg (unfert.)</AEXP_EggRockhopperPenguinUnfertilized.label>
  <!-- EN: An unfertilized rockhopper penguin egg. It can be eaten raw, but it's much better cooked. -->
  <AEXP_EggRockhopperPenguinUnfertilized.description>Неоплодотворённое яйцо хохлатого пингвина. Может быть съедено сырым, но приготовленное оно гораздо вкуснее.</AEXP_EggRockhopperPenguinUnfertilized.description>

</LanguageData>