<?xml version="1.0" encoding="utf-8"?>
<LanguageData>

  <VCE_CookBakeSimple.label>cook simple bake x2</VCE_CookBakeSimple.label>
  <VCE_CookBakeSimple.description>Cook two simple bakes quickly cooked from flour.</VCE_CookBakeSimple.description>
  <VCE_CookBakeSimple.jobString>Cooking simple bake x2.</VCE_CookBakeSimple.jobString>

  <VCE_CookBakeSimpleBulk.label>cook simple bake x8</VCE_CookBakeSimpleBulk.label>
  <VCE_CookBakeSimpleBulk.description>Cook 8 simple bakes quickly cooked from flour.</VCE_CookBakeSimpleBulk.description>
  <VCE_CookBakeSimpleBulk.jobString>Cooking simple bake x8.</VCE_CookBakeSimpleBulk.jobString>

  <VCE_CookBakeFine.label>cook fine bake x2</VCE_CookBakeFine.label>
  <VCE_CookBakeFine.description>Cook two complex bakes assembled with care from a wide selection of ingredients and flour.</VCE_CookBakeFine.description>
  <VCE_CookBakeFine.jobString>Cooking fine bake x2.</VCE_CookBakeFine.jobString>

  <VCE_CookBakeFineBulk.label>cook fine bake x8</VCE_CookBakeFineBulk.label>
  <VCE_CookBakeFineBulk.description>Cook 8 complex bakes assembled with care from a wide selection of ingredients and flour.</VCE_CookBakeFineBulk.description>
  <VCE_CookBakeFineBulk.jobString>Cooking fine bake x8.</VCE_CookBakeFineBulk.jobString>

  <VCE_CookBakeLavish.label>cook lavish bake x2</VCE_CookBakeLavish.label>
  <VCE_CookBakeLavish.description>Cook two masterpieces of the culinary arts, these bakes nourish the body, mind, and soul.</VCE_CookBakeLavish.description>
  <VCE_CookBakeLavish.jobString>Cooking lavish bake x2.</VCE_CookBakeLavish.jobString>

  <VCE_CookBakeLavishBulk.label>cook lavish bake x8</VCE_CookBakeLavishBulk.label>
  <VCE_CookBakeLavishBulk.description>Cook 8 masterpieces of the culinary arts, these bakes nourish the body, mind, and soul.</VCE_CookBakeLavishBulk.description>
  <VCE_CookBakeLavishBulk.jobString>Cooking lavish bake x8.</VCE_CookBakeLavishBulk.jobString>

  <VCE_CookBakeGourmet.label>cook gourmet bake x2</VCE_CookBakeGourmet.label>
  <VCE_CookBakeGourmet.description>Cook two culinary works of art, characterized by refined, even elaborate preparation and presentation of an aesthetically balanced, albeit low quantity bake.\n\nThis recipe does not allow mixed ingredients.</VCE_CookBakeGourmet.description>
  <VCE_CookBakeGourmet.jobString>Cooking gourmet bake x2.</VCE_CookBakeGourmet.jobString>


</LanguageData>