<?xml version="1.0" encoding="utf-8"?>
<LanguageData>
  <!-- EN: basic furniture -->
  <MF_BasicFurniture.label>сборка простой мебели</MF_BasicFurniture.label>
  <!-- EN: Build simple furniture like simple beds, basic tables, stools, benches and more. -->
  <MF_BasicFurniture.description>Сборка мебели простой конструкции: коек, столов, стульев, скамеек и прочего.</MF_BasicFurniture.description>
  
   <!-- EN: 
		<li>subject->foundations of comfort</li>
		<li>subject_story->rediscovered ancient techniques for crafting durable, essential furniture</li>
		<li>subject_story->pioneered the use of local materials to create comfortable living spaces</li>
		<li>subject_story->taught the community the value of crafting with nature, not against it</li>
		<li>subject_story->initiated the tradition of communal gatherings around the hearth and table</li>
		<li>subject_gerund->establishing the basics of homely comfort and utility</li>
 
  <MF_BasicFurniture.generalRules.rulesStrings>
		<li>subject->foundations of comfort</li>
		<li>subject_story->rediscovered ancient techniques for crafting durable, essential furniture</li>
		<li>subject_story->pioneered the use of local materials to create comfortable living spaces</li>
		<li>subject_story->taught the community the value of crafting with nature, not against it</li>
		<li>subject_story->initiated the tradition of communal gatherings around the hearth and table</li>
		<li>subject_gerund->establishing the basics of homely comfort and utility</li>
  </MF_BasicFurniture.generalRules.rulesStrings>   -->

  <!-- EN: artisan furniture -->
  <MF_RoyalFurniture.label>изысканная мебель</MF_RoyalFurniture.label>
  <!-- EN: Build luxury furniture focused strongly on aesthetics and beauty over practicality, usually only seen in the houses of the wealthy elite. Including poster beds, royal chairs, tables and armchairs. -->
  <MF_RoyalFurniture.description>Изготовление роскошной мебели, которую можно увидеть только в богатых домах: роскошных кроватей с балдахином, роскошных стульев, столов и кресел. При создании такой мебели основное внимание уделяется её эстетической ценности, а не функциональности.</MF_RoyalFurniture.description>
  
  <!-- EN: 
		<li>subject->the art of luxury</li>
		<li>subject_story->reclaimed forgotten methods of inlay and marquetry for exquisite pieces</li>
		<li>subject_story->fostered a new age of craftsmanship, blending beauty with utility</li>
		<li>subject_story->commissioned pieces that would become the envy of visiting dignitaries</li>
		<li>subject_story->inspired artisans to push the boundaries of design and materials</li>
		<li>subject_story->created spaces of unparalleled elegance, reflecting the pinnacle of culture</li>
		<li>subject_gerund->crafting symbols of status and artistry</li>

  <MF_RoyalFurniture.generalRules.rulesStrings>
		<li>subject->the art of luxury</li>
		<li>subject_story->reclaimed forgotten methods of inlay and marquetry for exquisite pieces</li>
		<li>subject_story->fostered a new age of craftsmanship, blending beauty with utility</li>
		<li>subject_story->commissioned pieces that would become the envy of visiting dignitaries</li>
		<li>subject_story->inspired artisans to push the boundaries of design and materials</li>
		<li>subject_story->created spaces of unparalleled elegance, reflecting the pinnacle of culture</li>
		<li>subject_gerund->crafting symbols of status and artistry</li>
  </MF_RoyalFurniture.generalRules.rulesStrings>    -->

  <!-- EN: modern furniture -->
  <MF_ModernFurniture.label>современная мебель</MF_ModernFurniture.label>
  <!-- EN: Learn to build furniture of the modern day that is focused on practicality over beauty, such as roulette tables, wardrobes, dart boards, punching bags and ergonomic beds. -->
  <MF_ModernFurniture.description>Изготовление современных предметов обстановки, ориентированных на практичность, а не на красоту: эргономичных кроватей, шифоньеров, боксёрских груш, столов для рулетки и мишеней для Дартс.</MF_ModernFurniture.description>
  
  <!-- EN: 
		<li>subject->practical elegance</li>
		<li>subject_story->embraced the fusion of form and function to suit modern lifestyles</li>
		<li>subject_story->innovated with new materials for durability and comfort</li>
		<li>subject_story->prioritized ergonomic designs to enhance daily living</li>
		<li>subject_story->introduced concepts of modular and space-saving furniture</li>
		<li>subject_story->championed the minimalist aesthetic, focusing on simplicity and practicality</li>
		<li>subject_gerund->redefining living spaces for the contemporary era</li>

  <MF_ModernFurniture.generalRules.rulesStrings>
		<li>subject->practical elegance</li>
		<li>subject_story->embraced the fusion of form and function to suit modern lifestyles</li>
		<li>subject_story->innovated with new materials for durability and comfort</li>
		<li>subject_story->prioritized ergonomic designs to enhance daily living</li>
		<li>subject_story->introduced concepts of modular and space-saving furniture</li>
		<li>subject_story->championed the minimalist aesthetic, focusing on simplicity and practicality</li>
		<li>subject_gerund->redefining living spaces for the contemporary era</li>
  </MF_ModernFurniture.generalRules.rulesStrings>    -->

  <!-- EN: waste disposal -->
  <MF_WasteDisposal.label>утилизация отходов</MF_WasteDisposal.label>
  <!-- EN: Learn to build small and large bins, objects that slowly clean the environment they are in. -->
  <MF_WasteDisposal.description>Изготовление мусорных баков и контейнеров, которые медленно очищают пространство вокруг себя.</MF_WasteDisposal.description>
  
   <!-- EN: 
		<li>subject->the cleanliness revolution</li>
		<li>subject_story->developed efficient waste management solutions to promote hygiene</li>
		<li>subject_story->introduced the concept of recycling, transforming waste into resources</li>
		<li>subject_story->engineered bins that integrate seamlessly into both public and private spaces</li>
		<li>subject_story->pioneered waste processing techniques that minimize environmental impact</li>
		<li>subject_story->catalyzed a cultural shift towards sustainability and cleanliness</li>
		<li>subject_gerund->enhancing communities with smart waste solutions</li>

  <MF_WasteDisposal.generalRules.rulesStrings>
		<li>subject->the cleanliness revolution</li>
		<li>subject_story->developed efficient waste management solutions to promote hygiene</li>
		<li>subject_story->introduced the concept of recycling, transforming waste into resources</li>
		<li>subject_story->engineered bins that integrate seamlessly into both public and private spaces</li>
		<li>subject_story->pioneered waste processing techniques that minimize environmental impact</li>
		<li>subject_story->catalyzed a cultural shift towards sustainability and cleanliness</li>
		<li>subject_gerund->enhancing communities with smart waste solutions</li>
  </MF_WasteDisposal.generalRules.rulesStrings>    -->
  
  <!-- EN: basic electronics -->
  <TubeTelevision.label>электронные развлечения</TubeTelevision.label>
  <!-- EN: Build basic electronic joy sources such as tube televisions, industrial radios, arcades and more. -->
  <TubeTelevision.description>Изготовление простых электронных устройств для развлечения: ЭЛТ-телевизоров, винтажных радио, аркадных автоматов и прочего.</TubeTelevision.description>

  <!-- EN: complex electronics -->
  <FlatscreenTelevision.label>продвинутые электронные развлечения</FlatscreenTelevision.label>
  <!-- EN: Build complex electronic joy sources such as flatscreen televisions, longwave radios and more. -->
  <FlatscreenTelevision.description>Изготовление сложных электронных устройств для развлечения: ЖК-телевизоров, радиоприёмников и прочего.</FlatscreenTelevision.description>
</LanguageData>