<?xml version="1.0" encoding="utf-8"?>
<ModMetaData>
  <name>Vanilla Animals Expanded Russian Language Pack</name>
  <author>Mewn Goddess</author>
  <supportedVersions>
    <li>1.4</li>
    <li>1.5</li>
  </supportedVersions>
  <packageId>Mewn.RU.ANIMALS</packageId>
  <description>Перевод на русский язык всех модулей серии Vanilla Animals Expanded. Подробности ищите на странице в мастерской.</description>
  <loadAfter>
    <li>VanillaExpanded.VAERoy</li>
    <li>VanillaExpanded.VAECaves</li>
    <li>VanillaExpanded.VAEEndAndExt</li>
    <li>VanillaExpanded.VanillaAnimalsExpanded</li>
    <li>VanillaExpanded.VAEWaste</li>
  </loadAfter>
  <incompatibleWith>
    <li>Inoshishi3.VAE.RusPatch</li>
    <li>Am.Rus.VAE</li>
    <li>kamikadza13.vanillaexpanded.vaeroy</li>
  </incompatibleWith>
</ModMetaData>